thesisquality/__init__.py
thesisquality/cli.py
thesisquality/core.py
thesisquality-0.0.3.dist-info/licenses/LICENSES/LICENSE-Apache-2.0.txt
thesisquality-0.0.3.dist-info/licenses/LICENSES/LICENSE-BSD-3-Clause.txt
thesisquality-0.0.3.dist-info/licenses/LICENSES/LICENSE-MIT.txt
thesisquality-0.0.3.dist-info/METADATA
thesisquality-0.0.3.dist-info/WHEEL
thesisquality-0.0.3.dist-info/entry_points.txt
thesisquality-0.0.3.dist-info/top_level.txt
thesisquality-0.0.3.dist-info/RECORD
